[
 {
  "player_id": 95715,
  "player_name": "Lucas Moura",
  "position": "midfielder",
  "team_id_1": 6,
  "team_name_1": "Tottenham Hotspur",
  "team_id_2": null,
  "team_name_2": null,
  "Height": 1.7272,
  "Weight": 72.121128
 },
 {
  "player_id": 80226,
  "player_name": "Serge Aurier",
  "position": "defender",
  "team_id_1": 6,
  "team_name_1": "Tottenham Hotspur",
  "team_id_2": null,
  "team_name_2": null,
  "Height": 1.7526,
  "Weight": 76.203456
 },
 {
  "player_id": 85971,
  "player_name": "Son Heung-Min",
  "position": "midfielder",
  "team_id_1": 6,
  "team_name_1": "Tottenham Hotspur",
  "team_id_2": null,
  "team_name_2": null,
  "Height": 1.8288,
  "Weight": 78.017824
 },
 {
  "player_id": 87835,
  "player_name": "Matt Doherty",
  "position": "defender",
  "team_id_1": 6,
  "team_name_1": "Tottenham Hotspur",
  "team_id_2": null,
  "team_name_2": null,
  "Height": 1.8542,
  "Weight": 79.832192
 },
 {
  "player_id": 132015,
  "player_name": "Pierre-Emile Holjbjerg",
  "position": "midfielder",
  "team_id_1": 6,
  "team_name_1": "Tottenham Hotspur",
  "team_id_2": null,
  "team_name_2": null,
  "Height": 1.8542,
  "Weight": 81.192968
 },
 {
  "player_id": 36903,
  "player_name": "Gareth Bale",
  "position": "midfielder",
  "team_id_1": 6,
  "team_name_1": "Tottenham Hotspur",
  "team_id_2": null,
  "team_name_2": null,
  "Height": 1.8542,
  "Weight": 81.64656
 },
 {
  "player_id": 37915,
  "player_name": "Hugo Lloris",
  "position": "goalkeeper",
  "team_id_1": 6,
  "team_name_1": "Tottenham Hotspur",
  "team_id_2": null,
  "team_name_2": null,
  "Height": 1.8796,
  "Weight": 78.017824
 },
 {
  "player_id": 55605,
  "player_name": "Toby Alderweireld",
  "position": "defender",
  "team_id_1": 6,
  "team_name_1": "Tottenham Hotspur",
  "team_id_2": null,
  "team_name_2": null,
  "Height": 1.8796,
  "Weight": 91.171992
 },
 {
  "player_id": 93264,
  "player_name": "Eric Dier",
  "position": "defender",
  "team_id_1": 6,
  "team_name_1": "Tottenham Hotspur",
  "team_id_2": null,
  "team_name_2": null,
  "Height": 1.8796,
  "Weight": 89.811216
 },
 {
  "player_id": 78830,
  "player_name": "Harry Kane",
  "position": "forward",
  "team_id_1": 6,
  "team_name_1": "Tottenham Hotspur",
  "team_id_2": null,
  "team_name_2": null,
  "Height": 1.8796,
  "Weight": 85.275296
 },
 {
  "player_id": 108823,
  "player_name": "Dele Alli",
  "position": "midfielder",
  "team_id_1": 6,
  "team_name_1": "Tottenham Hotspur",
  "team_id_2": null,
  "team_name_2": null,
  "Height": 1.8796,
  "Weight": 79.3786
 },
 {
  "player_id": 45268,
  "player_name": "Moussa Sissoko",
  "position": "midfielder",
  "team_id_1": 6,
  "team_name_1": "Tottenham Hotspur",
  "team_id_2": null,
  "team_name_2": null,
  "Height": 1.8796,
  "Weight": 90.7184
 },
 {
  "player_id": 173904,
  "player_name": "Davinson Sanchez",
  "position": "defender",
  "team_id_1": 6,
  "team_name_1": "Tottenham Hotspur",
  "team_id_2": null,
  "team_name_2": null,
  "Height": 1.8796,
  "Weight": 81.192968
 },
 {
  "player_id": 245824,
  "player_name": "Carlos Vinicius",
  "position": "forward",
  "team_id_1": 6,
  "team_name_1": "Tottenham Hotspur",
  "team_id_2": null,
  "team_name_2": null,
  "Height": 1.905,
  "Weight": 86.18248
 },
 {
  "player_id": 214225,
  "player_name": "Joe Rodon",
  "position": "defender",
  "team_id_1": 6,
  "team_name_1": "Tottenham Hotspur",
  "team_id_2": null,
  "team_name_2": null,
  "Height": 1.9304,
  "Weight": 69.853168
 },
 {
  "player_id": 157668,
  "player_name": "Harry Winks",
  "position": "midfielder",
  "team_id_1": 6,
  "team_name_1": "Tottenham Hotspur",
  "team_id_2": null,
  "team_name_2": null,
  "Height": 1.778,
  "Weight": 64.863656
 },
 {
  "player_id": 194252,
  "player_name": "Steven Bergwijn",
  "position": "midfielder",
  "team_id_1": 6,
  "team_name_1": "Tottenham Hotspur",
  "team_id_2": null,
  "team_name_2": null,
  "Height": 1.778,
  "Weight": 78.017824
 },
 {
  "player_id": 200826,
  "player_name": "Giovani Lo Celso",
  "position": "midfielder",
  "team_id_1": 6,
  "team_name_1": "Tottenham Hotspur",
  "team_id_2": null,
  "team_name_2": null,
  "Height": 1.778,
  "Weight": 68.0388
 },
 {
  "player_id": 199249,
  "player_name": "Sergio Reguilion",
  "position": "defender",
  "team_id_1": 6,
  "team_name_1": "Tottenham Hotspur",
  "team_id_2": null,
  "team_name_2": null,
  "Height": 1.778,
  "Weight": 67.131616
 },
 {
  "player_id": 115556,
  "player_name": "Ben Davies",
  "position": "defender",
  "team_id_1": 6,
  "team_name_1": "Tottenham Hotspur",
  "team_id_2": null,
  "team_name_2": null,
  "Height": 1.8034,
  "Weight": 76.203456
 },
 {
  "player_id": 231372,
  "player_name": "Tanguy Ndombele",
  "position": "midfielder",
  "team_id_1": 6,
  "team_name_1": "Tottenham Hotspur",
  "team_id_2": null,
  "team_name_2": null,
  "Height": 1.8034,
  "Weight": 76.203456
 },
 {
  "player_id": 62974,
  "player_name": "Erik Lamela",
  "position": "forward",
  "team_id_1": 6,
  "team_name_1": "Tottenham Hotspur",
  "team_id_2": null,
  "team_name_2": null,
  "Height": 1.8034,
  "Weight": 78.925008
 },
 {
  "player_id": 199584,
  "player_name": "Japhet Tanganga",
  "position": "defender",
  "team_id_1": 6,
  "team_name_1": "Tottenham Hotspur",
  "team_id_2": null,
  "team_name_2": null,
  "Height": 1.86,
  "Weight": 83
 }
]